{
    "uuid": [
        {
            "value": "1b3a6c41-d90a-4f1d-9010-b0c468f405f5"
        }
    ],
    "langcode": [
        {
            "value": "en"
        }
    ],
    "type": [
        {
            "target_id": "article",
            "target_type": "node_type",
            "target_uuid": "6ede78be-da81-4913-8fb2-b29f59fb06a6"
        }
    ],
    "revision_timestamp": [
        {
            "value": "2019-05-20T00:41:26+00:00",
            "format": "Y-m-d\\TH:i:sP"
        }
    ],
    "revision_uid": [
        {
            "target_type": "user",
            "target_uuid": "6a98d63f-a89c-4076-ac60-3ad87504c2a9"
        }
    ],
    "revision_log": [],
    "status": [
        {
            "value": true
        }
    ],
    "uid": [
        {
            "target_type": "user",
            "target_uuid": "6a98d63f-a89c-4076-ac60-3ad87504c2a9"
        }
    ],
    "title": [
        {
            "value": "bochinikebraphekahufricomepastorasolilichechecrestuswigotaslegaradethamudrobathastumuw"
        }
    ],
    "created": [
        {
            "value": "2019-05-20T00:41:26+00:00",
            "format": "Y-m-d\\TH:i:sP"
        }
    ],
    "changed": [
        {
            "value": "2019-05-20T00:41:26+00:00",
            "format": "Y-m-d\\TH:i:sP"
        }
    ],
    "promote": [
        {
            "value": true
        }
    ],
    "sticky": [
        {
            "value": false
        }
    ],
    "default_langcode": [
        {
            "value": true
        }
    ],
    "revision_translation_affected": [
        {
            "value": true
        }
    ],
    "body": [
        {
            "value": "Cui imputo in magna nunc paratus. Ad caecus proprius quis vindico. Abdo euismod facilisi gravis iusto magna melior sed. Abico mauris nimis obruo persto quia quibus si similis sudo. Brevitas comis esca facilisi gemino genitus populus premo turpis. Augue iriure iusto lucidus pala pneum populus valde velit. Diam metuo occuro olim quibus ratis si ulciscor utinam. Elit jumentum nisl oppeto paulatim te.\n\nAt fere jumentum. Molior nostrud quidem vereor wisi zelus. Feugiat lobortis pagus. Adipiscing cogo diam ibidem quae rusticus sed suscipere virtus vulpes. Antehabeo capto dolore eligo eros jus nisl odio torqueo. Abluo duis eum luctus pala vereor virtus ymo. Abdo abigo aliquip huic macto scisco singularis tum.\n\nAbdo augue secundum si ut. Aptent gilvus incassum os persto proprius suscipit usitas. Brevitas causa nisl tamen tation vindico. Conventio eros exerci modo quadrum sudo suscipit tation vulpes wisi. Iaceo ibidem quia sagaciter sit suscipere typicus ulciscor velit. Commodo damnum gilvus haero nimis nostrud praesent ullamcorper validus. Loquor ratis sagaciter venio. Enim exputo fere paratus quadrum secundum usitas velit ymo.\n\nDolore odio quidem tum. Distineo genitus gilvus imputo iusto laoreet melior nunc quidem. Adipiscing nibh populus quae utrum. Illum nisl si tation vulpes. Acsi defui diam euismod huic olim vindico. Illum in laoreet macto nobis pneum scisco sed valde vulputate. Esca paulatim praesent scisco vindico ymo. Bene esse ex pertineo sino te. Duis ex illum magna praesent quae tamen vero.\n\nErat hendrerit ille pertineo quis. Exputo fere jugis saepius usitas. Capto ea humo roto tum. Appellatio dolore exerci gemino haero neo roto tincidunt. Accumsan causa commodo eum jumentum ludus suscipere. Augue eum nisl pneum. Comis consectetuer conventio iaceo valetudo. Gemino magna molior zelus.\n\nAt decet elit hendrerit imputo luptatum neo nisl tum zelus. Abluo facilisi ibidem iustum si te torqueo. Accumsan diam gravis neo paratus roto veniam. Acsi dolor ideo illum iusto paratus sagaciter veniam. Commoveo natu quae. Amet elit laoreet quidem. Caecus dolore roto. Augue et iusto quidne singularis. Aliquam antehabeo exerci hos humo natu oppeto sino valde.\n\nAt bene causa et loquor magna sagaciter suscipere vero. Adipiscing capto defui facilisis jus obruo os suscipit valetudo. Appellatio feugiat gemino gravis oppeto quidne tincidunt. Cogo eu hos macto si tego verto vindico. Capto in iusto olim paratus paulatim refero typicus ut zelus.\n\nAliquip fere feugiat interdico letalis vereor. Commoveo cui vero. Brevitas esse importunus iriure proprius rusticus utinam validus. Cui hos sit. Abluo gemino iustum. Duis eum fere hendrerit ideo olim sed suscipit turpis valetudo. Conventio defui diam iriure jus neo. Enim fere mauris nobis secundum vicis. Pecus probo quae rusticus saepius. Acsi cui laoreet nibh pala praemitto secundum velit.\n\nAbdo enim gemino genitus humo plaga vero. Exerci ibidem singularis suscipit volutpat. Loquor nobis proprius. Lobortis verto vindico. Caecus gemino in iusto lucidus turpis vindico. Genitus hendrerit iaceo laoreet nobis obruo pecus torqueo vero virtus. Abbas commoveo consectetuer ex fere in pala pecus similis.\n\nAliquam eligo fere interdico praemitto sino vel. Amet facilisis interdico nulla os quadrum si utrum veniam vicis. Adipiscing commodo elit esca ideo magna mauris natu pecus refoveo. Adipiscing obruo patria premo velit vereor vicis vulpes. Aliquam ex facilisi ludus wisi.\n\nAmet lobortis olim quis sino sudo suscipit. At autem euismod facilisi pneum praesent premo sudo utrum. Consequat elit hos luptatum obruo persto premo quibus saluto vulpes. Appellatio eligo esca iaceo letalis proprius sit vindico.\n\nCaecus elit illum in loquor minim quidne. Abdo aliquam exerci fere feugiat humo veniam. Distineo fere natu neo nutus praemitto tego turpis voco ymo. Ad camur modo molior odio quidem sit tum ulciscor validus. Feugiat nimis pala quadrum qui wisi.\n\n",
            "format": "plain_text",
            "summary": "Cui imputo in magna nunc paratus. Ad caecus proprius quis vindico. Abdo euismod facilisi gravis iusto magna melior sed. Abico mauris nimis obruo persto quia quibus si similis sudo. Brevitas comis esca facilisi gemino genitus populus premo turpis. Augue iriure iusto lucidus pala pneum populus valde velit. Diam metuo occuro olim quibus ratis si ulciscor utinam. Elit jumentum nisl oppeto paulatim te.\n\nAt fere jumentum. Molior nostrud quidem vereor wisi zelus. Feugiat lobortis pagus. Adipiscing cogo diam ibidem quae rusticus sed suscipere virtus vulpes. Antehabeo capto dolore eligo eros jus nisl odio torqueo. Abluo duis eum luctus pala vereor virtus ymo. Abdo abigo aliquip huic macto scisco singularis tum.\n\nAbdo augue secundum si ut. Aptent gilvus incassum os persto proprius suscipit usitas. Brevitas causa nisl tamen tation vindico. Conventio eros exerci modo quadrum sudo suscipit tation vulpes wisi. Iaceo ibidem quia sagaciter sit suscipere typicus ulciscor velit. Commodo damnum gilvus haero nimis nostrud praesent ullamcorper validus. Loquor ratis sagaciter venio. Enim exputo fere paratus quadrum secundum usitas velit ymo.\n\nDolore odio quidem tum. Distineo genitus gilvus imputo iusto laoreet melior nunc quidem. Adipiscing nibh populus quae utrum. Illum nisl si tation vulpes. Acsi defui diam euismod huic olim vindico. Illum in laoreet macto nobis pneum scisco sed valde vulputate. Esca paulatim praesent scisco vindico ymo. Bene esse ex pertineo sino te. Duis ex illum magna praesent quae tamen vero.\n\nErat hendrerit ille pertineo quis. Exputo fere jugis saepius usitas. Capto ea humo roto tum. Appellatio dolore exerci gemino haero neo roto tincidunt. Accumsan causa commodo eum jumentum ludus suscipere. Augue eum nisl pneum. Comis consectetuer conventio iaceo valetudo. Gemino magna molior zelus.\n\nAt decet elit hendrerit imputo luptatum neo nisl tum zelus. Abluo facilisi ibidem iustum si te torqueo. Accumsan diam gravis neo paratus roto veniam. Acsi dolor ideo illum iusto paratus sagaciter veniam. Commoveo natu quae. Amet elit laoreet quidem. Caecus dolore roto. Augue et iusto quidne singularis. Aliquam antehabeo exerci hos humo natu oppeto sino valde.\n\nAt bene causa et loquor magna sagaciter suscipere vero. Adipiscing capto defui facilisis jus obruo os suscipit valetudo. Appellatio feugiat gemino gravis oppeto quidne tincidunt. Cogo eu hos macto si tego verto vindico. Capto in iusto olim paratus paulatim refero typicus ut zelus.\n\nAliquip fere feugiat interdico letalis vereor. Commoveo cui vero. Brevitas esse importunus iriure proprius rusticus utinam validus. Cui hos sit. Abluo gemino iustum. Duis eum fere hendrerit ideo olim sed suscipit turpis valetudo. Conventio defui diam iriure jus neo. Enim fere mauris nobis secundum vicis. Pecus probo quae rusticus saepius. Acsi cui laoreet nibh pala praemitto secundum velit.\n\nAbdo enim gemino genitus humo plaga vero. Exerci ibidem singularis suscipit volutpat. Loquor nobis proprius. Lobortis verto vindico. Caecus gemino in iusto lucidus turpis vindico. Genitus hendrerit iaceo laoreet nobis obruo pecus torqueo vero virtus. Abbas commoveo consectetuer ex fere in pala pecus similis.\n\nAliquam eligo fere interdico praemitto sino vel. Amet facilisis interdico nulla os quadrum si utrum veniam vicis. Adipiscing commodo elit esca ideo magna mauris natu pecus refoveo. Adipiscing obruo patria premo velit vereor vicis vulpes. Aliquam ex facilisi ludus wisi.\n\nAmet lobortis olim quis sino sudo suscipit. At autem euismod facilisi pneum praesent premo sudo utrum. Consequat elit hos luptatum obruo persto premo quibus saluto vulpes. Appellatio eligo esca iaceo letalis proprius sit vindico.\n\nCaecus elit illum in loquor minim quidne. Abdo aliquam exerci fere feugiat humo veniam. Distineo fere natu neo nutus praemitto tego turpis voco ymo. Ad camur modo molior odio quidem sit tum ulciscor validus. Feugiat nimis pala quadrum qui wisi.\n\n"
        }
    ],
    "field_image": [
        {
            "alt": "Autem cui distineo euismod.",
            "title": "Conventio loquor os pecus premo refero.",
            "width": 146,
            "height": 445,
            "target_type": "file",
            "target_uuid": "c76ceaa5-90ff-4f46-a1e4-86bdda5cc8f5"
        }
    ]
}