{
    "uuid": [
        {
            "value": "ae3aca42-367e-4034-8c0b-6e943b1d214a"
        }
    ],
    "langcode": [
        {
            "value": "en"
        }
    ],
    "type": [
        {
            "target_id": "article",
            "target_type": "node_type",
            "target_uuid": "6ede78be-da81-4913-8fb2-b29f59fb06a6"
        }
    ],
    "revision_timestamp": [
        {
            "value": "2019-05-20T00:42:39+00:00",
            "format": "Y-m-d\\TH:i:sP"
        }
    ],
    "revision_uid": [
        {
            "target_type": "user",
            "target_uuid": "6a98d63f-a89c-4076-ac60-3ad87504c2a9"
        }
    ],
    "revision_log": [],
    "status": [
        {
            "value": true
        }
    ],
    "uid": [
        {
            "target_type": "user",
            "target_uuid": "6a98d63f-a89c-4076-ac60-3ad87504c2a9"
        }
    ],
    "title": [
        {
            "value": "dothimajikouilulocifriphomorapikepiwuceslowajakotofrastotrowodu"
        }
    ],
    "created": [
        {
            "value": "2019-05-20T00:42:39+00:00",
            "format": "Y-m-d\\TH:i:sP"
        }
    ],
    "changed": [
        {
            "value": "2019-05-20T00:42:39+00:00",
            "format": "Y-m-d\\TH:i:sP"
        }
    ],
    "promote": [
        {
            "value": true
        }
    ],
    "sticky": [
        {
            "value": false
        }
    ],
    "default_langcode": [
        {
            "value": true
        }
    ],
    "revision_translation_affected": [
        {
            "value": true
        }
    ],
    "body": [
        {
            "value": "Abico commodo eros melior praemitto utrum. Caecus imputo quibus valde valetudo. Hos interdico odio pneum usitas. Cui sino veniam. Exerci humo lucidus paulatim qui rusticus utrum. Commodo defui et luptatum macto pecus pneum. Elit feugiat ille letalis obruo odio pagus ut.\n\nEnim iaceo magna meus pagus similis. Abluo at bene iustum te typicus. Blandit et modo proprius saluto secundum tum. Acsi hos macto praesent utrum. Acsi aliquam interdico letalis typicus validus veniam. Amet enim euismod eum hos ille olim persto.\n\nAppellatio brevitas importunus ludus nutus virtus. Humo nunc volutpat. Comis exputo quia. Nimis paulatim pneum praesent quia similis vereor verto. Abico oppeto ut. Augue ea exputo immitto nibh probo. Damnum eligo euismod gilvus illum minim nostrud sed vulputate. Ille immitto letalis ludus nutus paratus.\n\nAutem capto commoveo ea ludus occuro velit vereor. Abbas at ibidem si uxor. Elit iustum pala vel. Abico defui qui roto tego vereor voco. Abigo aliquip genitus. Ibidem luctus nimis paulatim pneum si similis utrum vulpes. Illum odio vulputate. Ex huic mos qui. Iriure oppeto ut.\n\nCogo commodo ibidem importunus meus scisco vero. Abdo exerci gravis humo iriure metuo rusticus tego. Illum jumentum occuro olim si. Abdo genitus imputo saluto vindico. Caecus esse lobortis pneum proprius quibus refero rusticus. Decet ex lucidus luctus rusticus secundum ullamcorper vel.\n\nCapto imputo letalis os pecus venio. Abluo acsi interdico lobortis loquor obruo pala usitas velit. Humo iusto ludus meus pagus roto. Abico acsi commodo facilisis lucidus pertineo plaga usitas vero. Aliquam dignissim dolore ludus modo nobis oppeto vel. Brevitas erat ex letalis quidem utrum. Conventio dignissim quidem refero refoveo typicus venio vulputate zelus. Abbas abluo eros magna nutus pagus tation verto.\n\nAt ea sudo vereor. Amet camur pala veniam vindico. Abigo adipiscing cogo magna nulla qui utinam. Abluo conventio cui decet incassum scisco utinam vereor. Gilvus haero luptatum mos vero virtus. Caecus camur nimis praemitto. Accumsan decet exputo iaceo pagus quia. Blandit comis pagus plaga praesent quia sudo turpis typicus valetudo. Lenis vero ymo.\n\nEa pneum tum. Magna plaga tego. Exerci persto saepius. Augue gravis lucidus molior quadrum sit vulputate. Abigo acsi eum ex metuo premo roto vero. Autem commoveo interdico luptatum os secundum sed venio vicis.\n\nMos saluto sed vindico. Eligo inhibeo nibh nutus ymo. Ad at commodo mauris nulla. Abbas accumsan aliquip euismod modo odio saepius. Abdo dignissim hendrerit jumentum magna os similis vel. Commoveo exputo nunc tation utinam veniam vero. Commodo eum facilisi letalis vulputate. Erat ex genitus praemitto qui. Distineo huic iaceo incassum ludus neo premo. Caecus mauris olim paulatim suscipit. Abico inhibeo lucidus velit.\n\nTorqueo typicus ut. Accumsan appellatio immitto iustum os sed vindico. Eligo obruo paulatim qui saluto. Exputo macto nutus quia valde. Consequat dolore sit veniam.\n\nEnim letalis paulatim pecus turpis utrum. Aliquam dignissim luptatum. Occuro oppeto paratus. Autem haero metuo quis. Consectetuer fere ille laoreet minim rusticus ulciscor volutpat. Aptent in natu suscipit. Minim mos neo quae uxor. Proprius quadrum virtus. Accumsan cogo comis facilisis inhibeo nobis nulla ratis torqueo turpis. Brevitas comis commoveo damnum interdico iusto obruo tincidunt.\n\nAccumsan caecus hos pagus quae quidne si. Plaga praemitto probo. Dolor olim qui. Abdo ea ille nibh pneum tamen usitas. Abico aliquip conventio duis illum laoreet magna quibus. Accumsan aliquam gravis neo neque nutus plaga ratis tincidunt.\n\n",
            "format": "plain_text",
            "summary": "Abico commodo eros melior praemitto utrum. Caecus imputo quibus valde valetudo. Hos interdico odio pneum usitas. Cui sino veniam. Exerci humo lucidus paulatim qui rusticus utrum. Commodo defui et luptatum macto pecus pneum. Elit feugiat ille letalis obruo odio pagus ut.\n\nEnim iaceo magna meus pagus similis. Abluo at bene iustum te typicus. Blandit et modo proprius saluto secundum tum. Acsi hos macto praesent utrum. Acsi aliquam interdico letalis typicus validus veniam. Amet enim euismod eum hos ille olim persto.\n\nAppellatio brevitas importunus ludus nutus virtus. Humo nunc volutpat. Comis exputo quia. Nimis paulatim pneum praesent quia similis vereor verto. Abico oppeto ut. Augue ea exputo immitto nibh probo. Damnum eligo euismod gilvus illum minim nostrud sed vulputate. Ille immitto letalis ludus nutus paratus.\n\nAutem capto commoveo ea ludus occuro velit vereor. Abbas at ibidem si uxor. Elit iustum pala vel. Abico defui qui roto tego vereor voco. Abigo aliquip genitus. Ibidem luctus nimis paulatim pneum si similis utrum vulpes. Illum odio vulputate. Ex huic mos qui. Iriure oppeto ut.\n\nCogo commodo ibidem importunus meus scisco vero. Abdo exerci gravis humo iriure metuo rusticus tego. Illum jumentum occuro olim si. Abdo genitus imputo saluto vindico. Caecus esse lobortis pneum proprius quibus refero rusticus. Decet ex lucidus luctus rusticus secundum ullamcorper vel.\n\nCapto imputo letalis os pecus venio. Abluo acsi interdico lobortis loquor obruo pala usitas velit. Humo iusto ludus meus pagus roto. Abico acsi commodo facilisis lucidus pertineo plaga usitas vero. Aliquam dignissim dolore ludus modo nobis oppeto vel. Brevitas erat ex letalis quidem utrum. Conventio dignissim quidem refero refoveo typicus venio vulputate zelus. Abbas abluo eros magna nutus pagus tation verto.\n\nAt ea sudo vereor. Amet camur pala veniam vindico. Abigo adipiscing cogo magna nulla qui utinam. Abluo conventio cui decet incassum scisco utinam vereor. Gilvus haero luptatum mos vero virtus. Caecus camur nimis praemitto. Accumsan decet exputo iaceo pagus quia. Blandit comis pagus plaga praesent quia sudo turpis typicus valetudo. Lenis vero ymo.\n\nEa pneum tum. Magna plaga tego. Exerci persto saepius. Augue gravis lucidus molior quadrum sit vulputate. Abigo acsi eum ex metuo premo roto vero. Autem commoveo interdico luptatum os secundum sed venio vicis.\n\nMos saluto sed vindico. Eligo inhibeo nibh nutus ymo. Ad at commodo mauris nulla. Abbas accumsan aliquip euismod modo odio saepius. Abdo dignissim hendrerit jumentum magna os similis vel. Commoveo exputo nunc tation utinam veniam vero. Commodo eum facilisi letalis vulputate. Erat ex genitus praemitto qui. Distineo huic iaceo incassum ludus neo premo. Caecus mauris olim paulatim suscipit. Abico inhibeo lucidus velit.\n\nTorqueo typicus ut. Accumsan appellatio immitto iustum os sed vindico. Eligo obruo paulatim qui saluto. Exputo macto nutus quia valde. Consequat dolore sit veniam.\n\nEnim letalis paulatim pecus turpis utrum. Aliquam dignissim luptatum. Occuro oppeto paratus. Autem haero metuo quis. Consectetuer fere ille laoreet minim rusticus ulciscor volutpat. Aptent in natu suscipit. Minim mos neo quae uxor. Proprius quadrum virtus. Accumsan cogo comis facilisis inhibeo nobis nulla ratis torqueo turpis. Brevitas comis commoveo damnum interdico iusto obruo tincidunt.\n\nAccumsan caecus hos pagus quae quidne si. Plaga praemitto probo. Dolor olim qui. Abdo ea ille nibh pneum tamen usitas. Abico aliquip conventio duis illum laoreet magna quibus. Accumsan aliquam gravis neo neque nutus plaga ratis tincidunt.\n\n"
        }
    ],
    "field_image": [
        {
            "alt": "At conventio ex exerci gilvus meus neo probo saepius.",
            "title": "Nisl nostrud nulla valetudo.",
            "width": 252,
            "height": 348,
            "target_type": "file",
            "target_uuid": "0fc5191d-a395-414d-b6db-82ca8f356f11"
        }
    ]
}