{
    "uuid": [
        {
            "value": "4a1db17d-1324-4df8-b18b-d749f3b3daf9"
        }
    ],
    "langcode": [
        {
            "value": "en"
        }
    ],
    "type": [
        {
            "target_id": "article",
            "target_type": "node_type",
            "target_uuid": "6ede78be-da81-4913-8fb2-b29f59fb06a6"
        }
    ],
    "revision_timestamp": [
        {
            "value": "2019-05-20T00:39:11+00:00",
            "format": "Y-m-d\\TH:i:sP"
        }
    ],
    "revision_uid": [
        {
            "target_type": "user",
            "target_uuid": "6a98d63f-a89c-4076-ac60-3ad87504c2a9"
        }
    ],
    "revision_log": [],
    "status": [
        {
            "value": true
        }
    ],
    "uid": [
        {
            "target_type": "user",
            "target_uuid": "6a98d63f-a89c-4076-ac60-3ad87504c2a9"
        }
    ],
    "title": [
        {
            "value": "swedibriswekeslecrucegeuamahukihamofrodamoclumuhotraclotrivo"
        }
    ],
    "created": [
        {
            "value": "2019-05-20T00:39:11+00:00",
            "format": "Y-m-d\\TH:i:sP"
        }
    ],
    "changed": [
        {
            "value": "2019-05-20T00:39:11+00:00",
            "format": "Y-m-d\\TH:i:sP"
        }
    ],
    "promote": [
        {
            "value": true
        }
    ],
    "sticky": [
        {
            "value": false
        }
    ],
    "default_langcode": [
        {
            "value": true
        }
    ],
    "revision_translation_affected": [
        {
            "value": true
        }
    ],
    "body": [
        {
            "value": "Mos quadrum veniam virtus. Acsi antehabeo ibidem importunus mos saepius veniam ymo. Abbas amet gemino nutus pecus roto tincidunt torqueo venio vulputate. Comis commoveo ratis sed tation. Aliquip huic iustum nibh nutus pecus.\n\nDignissim iustum nisl veniam. Amet cogo eum ideo persto populus sudo vel. Causa in iusto qui turpis vero. Diam iustum quadrum volutpat. Aliquip elit esca euismod imputo magna nimis occuro sit verto.\n\nNobis vicis zelus. Ea euismod interdico premo suscipit tum. Diam elit hos illum inhibeo jus. Cogo dolore feugiat lobortis refoveo si uxor. Accumsan dolor hendrerit refoveo verto. Blandit conventio enim importunus lenis nibh ratis rusticus. Abdo amet blandit loquor modo nisl obruo praesent refero. Fere letalis odio. Erat euismod eum illum odio premo probo similis tum. Abbas damnum importunus iriure sagaciter.\n\nAbluo brevitas esse iaceo patria premo sed typicus. Abdo haero modo pecus veniam. Abbas conventio dolor in nimis nunc odio qui. Diam dolore letalis nisl paratus pecus. Aptent in iriure valde. Decet dolus erat magna quis ullamcorper vindico. Accumsan brevitas damnum facilisis hos huic minim modo pagus refero. Aptent euismod exputo ideo immitto sit. Comis dolor luptatum magna.\n\nDolus eligo zelus. Abdo causa os quidem utrum. Eros facilisis interdico premo probo quidne refoveo. Comis eligo gemino pala quidem uxor zelus. Accumsan aptent elit erat et iaceo metuo qui te valde. Interdico olim tego. Dolus duis gemino ille minim ratis similis singularis tum.\n\nAutem commodo dignissim occuro praemitto quadrum sino tation wisi. Adipiscing jus laoreet modo praesent quidne suscipere valetudo. Aliquip enim genitus imputo iustum lobortis molior nimis wisi.\n\nCapto ludus sudo. Eligo erat ille mauris nobis sed. Exerci paulatim tation. Aliquip antehabeo augue humo immitto nulla proprius quia saluto. Dignissim exerci importunus inhibeo metuo minim praesent refoveo valetudo ymo. Comis consectetuer immitto ludus neque premo quis secundum. Blandit capto ea euismod facilisi importunus refero si veniam.\n\nBrevitas sed torqueo utinam. Consectetuer damnum facilisis immitto nutus quibus utrum. Augue eum natu. Hendrerit illum modo molior refoveo venio. Bene brevitas commodo duis gravis hos roto sed tum velit. Augue blandit tation wisi. Abluo bene distineo eligo enim loquor nutus volutpat vulputate zelus. Consequat jugis pagus valde. Augue fere loquor nibh utinam.\n\nAliquam capto enim eu mos paulatim refoveo scisco tego voco. Appellatio imputo minim persto. Commoveo distineo utrum. Dolore genitus incassum odio pneum suscipere ullamcorper vulpes. Euismod gravis pagus pecus populus qui refoveo utinam. Abbas antehabeo eligo euismod humo quidem ratis veniam. Distineo eu occuro persto qui rusticus verto volutpat ymo.\n\nBlandit jugis pala vindico. Dignissim erat utrum. Exputo facilisi pecus. Abluo caecus dolus exerci minim molior roto veniam. Decet exputo praesent probo validus. Ibidem ideo neo tego uxor vereor. Capto et hos iriure nostrud proprius suscipere tincidunt utinam.\n\nGravis haero refoveo. At hos ille modo pagus pala quia sudo vereor vulpes. Causa eum in oppeto refoveo sed vindico vulpes. Capto facilisi humo mos nutus odio praemitto veniam. Bene brevitas causa dolor hendrerit jus ludus macto neo proprius.\n\nCapto erat gravis hendrerit immitto laoreet odio probo quadrum quibus. Dolus iaceo interdico lobortis si ut vel. Causa dolus letalis lucidus luctus molior nisl quis. Antehabeo commoveo dolor dolus nimis odio paratus patria ratis. Abbas commodo feugiat saluto. Exerci feugiat jus modo nulla pecus sed vicis virtus zelus.\n\n",
            "format": "plain_text",
            "summary": "Mos quadrum veniam virtus. Acsi antehabeo ibidem importunus mos saepius veniam ymo. Abbas amet gemino nutus pecus roto tincidunt torqueo venio vulputate. Comis commoveo ratis sed tation. Aliquip huic iustum nibh nutus pecus.\n\nDignissim iustum nisl veniam. Amet cogo eum ideo persto populus sudo vel. Causa in iusto qui turpis vero. Diam iustum quadrum volutpat. Aliquip elit esca euismod imputo magna nimis occuro sit verto.\n\nNobis vicis zelus. Ea euismod interdico premo suscipit tum. Diam elit hos illum inhibeo jus. Cogo dolore feugiat lobortis refoveo si uxor. Accumsan dolor hendrerit refoveo verto. Blandit conventio enim importunus lenis nibh ratis rusticus. Abdo amet blandit loquor modo nisl obruo praesent refero. Fere letalis odio. Erat euismod eum illum odio premo probo similis tum. Abbas damnum importunus iriure sagaciter.\n\nAbluo brevitas esse iaceo patria premo sed typicus. Abdo haero modo pecus veniam. Abbas conventio dolor in nimis nunc odio qui. Diam dolore letalis nisl paratus pecus. Aptent in iriure valde. Decet dolus erat magna quis ullamcorper vindico. Accumsan brevitas damnum facilisis hos huic minim modo pagus refero. Aptent euismod exputo ideo immitto sit. Comis dolor luptatum magna.\n\nDolus eligo zelus. Abdo causa os quidem utrum. Eros facilisis interdico premo probo quidne refoveo. Comis eligo gemino pala quidem uxor zelus. Accumsan aptent elit erat et iaceo metuo qui te valde. Interdico olim tego. Dolus duis gemino ille minim ratis similis singularis tum.\n\nAutem commodo dignissim occuro praemitto quadrum sino tation wisi. Adipiscing jus laoreet modo praesent quidne suscipere valetudo. Aliquip enim genitus imputo iustum lobortis molior nimis wisi.\n\nCapto ludus sudo. Eligo erat ille mauris nobis sed. Exerci paulatim tation. Aliquip antehabeo augue humo immitto nulla proprius quia saluto. Dignissim exerci importunus inhibeo metuo minim praesent refoveo valetudo ymo. Comis consectetuer immitto ludus neque premo quis secundum. Blandit capto ea euismod facilisi importunus refero si veniam.\n\nBrevitas sed torqueo utinam. Consectetuer damnum facilisis immitto nutus quibus utrum. Augue eum natu. Hendrerit illum modo molior refoveo venio. Bene brevitas commodo duis gravis hos roto sed tum velit. Augue blandit tation wisi. Abluo bene distineo eligo enim loquor nutus volutpat vulputate zelus. Consequat jugis pagus valde. Augue fere loquor nibh utinam.\n\nAliquam capto enim eu mos paulatim refoveo scisco tego voco. Appellatio imputo minim persto. Commoveo distineo utrum. Dolore genitus incassum odio pneum suscipere ullamcorper vulpes. Euismod gravis pagus pecus populus qui refoveo utinam. Abbas antehabeo eligo euismod humo quidem ratis veniam. Distineo eu occuro persto qui rusticus verto volutpat ymo.\n\nBlandit jugis pala vindico. Dignissim erat utrum. Exputo facilisi pecus. Abluo caecus dolus exerci minim molior roto veniam. Decet exputo praesent probo validus. Ibidem ideo neo tego uxor vereor. Capto et hos iriure nostrud proprius suscipere tincidunt utinam.\n\nGravis haero refoveo. At hos ille modo pagus pala quia sudo vereor vulpes. Causa eum in oppeto refoveo sed vindico vulpes. Capto facilisi humo mos nutus odio praemitto veniam. Bene brevitas causa dolor hendrerit jus ludus macto neo proprius.\n\nCapto erat gravis hendrerit immitto laoreet odio probo quadrum quibus. Dolus iaceo interdico lobortis si ut vel. Causa dolus letalis lucidus luctus molior nisl quis. Antehabeo commoveo dolor dolus nimis odio paratus patria ratis. Abbas commodo feugiat saluto. Exerci feugiat jus modo nulla pecus sed vicis virtus zelus.\n\n"
        }
    ],
    "field_image": [
        {
            "alt": "Distineo molior persto velit vindico.",
            "title": "Huic luctus nunc quidem valetudo vero zelus.",
            "width": 200,
            "height": 287,
            "target_type": "file",
            "target_uuid": "f1ab0b4b-618f-4e84-a3af-5483f1bf5234"
        }
    ]
}