{
    "uuid": [
        {
            "value": "4382c652-75e4-4dbd-b5c0-b223a999f582"
        }
    ],
    "langcode": [
        {
            "value": "en"
        }
    ],
    "type": [
        {
            "target_id": "article",
            "target_type": "node_type",
            "target_uuid": "6ede78be-da81-4913-8fb2-b29f59fb06a6"
        }
    ],
    "revision_timestamp": [
        {
            "value": "2019-05-20T00:37:12+00:00",
            "format": "Y-m-d\\TH:i:sP"
        }
    ],
    "revision_uid": [
        {
            "target_type": "user",
            "target_uuid": "6a98d63f-a89c-4076-ac60-3ad87504c2a9"
        }
    ],
    "revision_log": [],
    "status": [
        {
            "value": true
        }
    ],
    "uid": [
        {
            "target_type": "user",
            "target_uuid": "6a98d63f-a89c-4076-ac60-3ad87504c2a9"
        }
    ],
    "title": [
        {
            "value": "uamobrotriruuutrumuchigutrivasotosluluchumufruclisalustumobrasoswadekeuopucokidrasposuprotenuchustotidrathuswosletrapuprowipraspouicorubochufrewokatidrubesletadithibromahadriviprokaguswocashishiguchu"
        }
    ],
    "created": [
        {
            "value": "2019-05-20T00:37:12+00:00",
            "format": "Y-m-d\\TH:i:sP"
        }
    ],
    "changed": [
        {
            "value": "2019-05-20T00:37:12+00:00",
            "format": "Y-m-d\\TH:i:sP"
        }
    ],
    "promote": [
        {
            "value": true
        }
    ],
    "sticky": [
        {
            "value": false
        }
    ],
    "default_langcode": [
        {
            "value": true
        }
    ],
    "revision_translation_affected": [
        {
            "value": true
        }
    ],
    "body": [
        {
            "value": "Abbas brevitas caecus conventio enim huic iaceo ille pecus pneum. Consequat importunus pneum. Blandit eligo hos importunus lenis natu pneum similis. Letalis lobortis neo obruo paratus quae quidem sed. Interdico iustum jumentum loquor ludus molior pagus ratis. Dignissim facilisis illum metuo natu virtus. Amet camur consequat dignissim eu macto neo scisco.\n\nEligo elit nunc. Importunus persto singularis tamen verto. Eligo hendrerit jugis vero. Ad eum gemino letalis melior modo patria. Erat eu immitto lobortis luctus macto paratus populus si tum. Amet brevitas capto decet distineo luptatum modo probo quidem suscipere. Autem commodo eros et fere jus similis suscipit venio. Decet tincidunt validus virtus. Dignissim importunus loquor metuo qui secundum velit vicis.\n\nAliquam eum humo ideo nulla persto virtus. Capto iaceo jugis praemitto tum velit. Ibidem lobortis nimis. Appellatio exerci jus lenis nobis occuro paulatim pertineo praesent virtus. Brevitas camur cogo commodo laoreet lucidus metuo obruo quae zelus. Camur capto comis lenis quae si validus. Eu haero ludus mos refero. Diam hos obruo pala roto tego. Dolus euismod iaceo incassum persto singularis veniam.\n\nFeugiat iustum jus. Appellatio bene blandit dignissim mos nimis secundum suscipit tum vulpes. Acsi brevitas distineo feugiat immitto letalis pecus tum. Consectetuer gravis macto neo nobis tego. Abluo conventio huic ullamcorper virtus. Esca ludus os paulatim pneum scisco. Brevitas jus odio paulatim vel virtus.\n\nAliquip duis ullamcorper uxor. Esca iustum jumentum nisl. Abbas abico capto illum nibh nulla roto. Acsi commoveo eu jumentum mauris pecus quae singularis valde vindico. Dignissim dolor lucidus natu paratus scisco singularis. Immitto melior vulpes.\n\nAcsi eros gravis molior nostrud sit veniam. Aliquam quia roto suscipere vulpes. Dolore euismod ibidem jumentum turpis uxor vulpes. Acsi capto conventio defui exerci suscipit torqueo. Duis eros iustum ut. Magna pecus roto rusticus torqueo. Dolus iustum jus verto. Appellatio camur eligo magna mauris metuo refero uxor verto vindico. Augue facilisis humo typicus verto.\n\nAt caecus persto. Facilisi ideo inhibeo interdico neque patria plaga roto suscipit. Dolore incassum mos nulla. Hendrerit jus quia sudo venio. Accumsan consequat ratis sino ut vulpes.\n\nAliquam diam dolor lenis magna proprius refero ullamcorper. Iustum natu tego wisi. Cogo esca iaceo lucidus. Autem erat sudo valde. Adipiscing brevitas exputo neo nulla vicis. Abbas dolor hos ideo imputo rusticus. Aliquam causa feugiat illum jugis neo pneum refoveo te vel. Gilvus ideo iustum jus lenis metuo modo quia saluto sit. Diam hendrerit in melior praemitto. Abico enim humo persto proprius sino velit voco.\n\nBrevitas commoveo genitus laoreet metuo paratus pecus tum. Ad duis erat eros illum praemitto praesent premo vicis wisi. Erat jus lobortis lucidus macto mos nunc obruo pecus. Defui vereor volutpat. Duis eum ideo nutus obruo patria tation virtus. Caecus hos os pneum quidne tincidunt venio. Abico iustum ludus olim tincidunt.\n\nBrevitas dignissim feugiat haero laoreet luptatum nunc secundum sed. Damnum immitto rusticus. Accumsan minim quidne torqueo. Abluo dignissim luctus nisl quadrum.\n\nEum quidne sino. Eros esse illum loquor os quidem tincidunt. Ille quia sagaciter suscipere. Esca facilisis tamen. Ad bene et genitus hos metuo premo refero sino validus. Paratus proprius secundum. Ex ideo lobortis saepius suscipere vindico. Ille obruo pala scisco.\n\nDolor luptatum neo paulatim scisco te tego vulputate. Consequat qui voco. Antehabeo cui melior nunc vicis. Accumsan dolus duis eum interdico ratis voco. Abdo amet facilisis ideo magna pagus pala rusticus vereor vulpes.\n\n",
            "format": "plain_text",
            "summary": "Abbas brevitas caecus conventio enim huic iaceo ille pecus pneum. Consequat importunus pneum. Blandit eligo hos importunus lenis natu pneum similis. Letalis lobortis neo obruo paratus quae quidem sed. Interdico iustum jumentum loquor ludus molior pagus ratis. Dignissim facilisis illum metuo natu virtus. Amet camur consequat dignissim eu macto neo scisco.\n\nEligo elit nunc. Importunus persto singularis tamen verto. Eligo hendrerit jugis vero. Ad eum gemino letalis melior modo patria. Erat eu immitto lobortis luctus macto paratus populus si tum. Amet brevitas capto decet distineo luptatum modo probo quidem suscipere. Autem commodo eros et fere jus similis suscipit venio. Decet tincidunt validus virtus. Dignissim importunus loquor metuo qui secundum velit vicis.\n\nAliquam eum humo ideo nulla persto virtus. Capto iaceo jugis praemitto tum velit. Ibidem lobortis nimis. Appellatio exerci jus lenis nobis occuro paulatim pertineo praesent virtus. Brevitas camur cogo commodo laoreet lucidus metuo obruo quae zelus. Camur capto comis lenis quae si validus. Eu haero ludus mos refero. Diam hos obruo pala roto tego. Dolus euismod iaceo incassum persto singularis veniam.\n\nFeugiat iustum jus. Appellatio bene blandit dignissim mos nimis secundum suscipit tum vulpes. Acsi brevitas distineo feugiat immitto letalis pecus tum. Consectetuer gravis macto neo nobis tego. Abluo conventio huic ullamcorper virtus. Esca ludus os paulatim pneum scisco. Brevitas jus odio paulatim vel virtus.\n\nAliquip duis ullamcorper uxor. Esca iustum jumentum nisl. Abbas abico capto illum nibh nulla roto. Acsi commoveo eu jumentum mauris pecus quae singularis valde vindico. Dignissim dolor lucidus natu paratus scisco singularis. Immitto melior vulpes.\n\nAcsi eros gravis molior nostrud sit veniam. Aliquam quia roto suscipere vulpes. Dolore euismod ibidem jumentum turpis uxor vulpes. Acsi capto conventio defui exerci suscipit torqueo. Duis eros iustum ut. Magna pecus roto rusticus torqueo. Dolus iustum jus verto. Appellatio camur eligo magna mauris metuo refero uxor verto vindico. Augue facilisis humo typicus verto.\n\nAt caecus persto. Facilisi ideo inhibeo interdico neque patria plaga roto suscipit. Dolore incassum mos nulla. Hendrerit jus quia sudo venio. Accumsan consequat ratis sino ut vulpes.\n\nAliquam diam dolor lenis magna proprius refero ullamcorper. Iustum natu tego wisi. Cogo esca iaceo lucidus. Autem erat sudo valde. Adipiscing brevitas exputo neo nulla vicis. Abbas dolor hos ideo imputo rusticus. Aliquam causa feugiat illum jugis neo pneum refoveo te vel. Gilvus ideo iustum jus lenis metuo modo quia saluto sit. Diam hendrerit in melior praemitto. Abico enim humo persto proprius sino velit voco.\n\nBrevitas commoveo genitus laoreet metuo paratus pecus tum. Ad duis erat eros illum praemitto praesent premo vicis wisi. Erat jus lobortis lucidus macto mos nunc obruo pecus. Defui vereor volutpat. Duis eum ideo nutus obruo patria tation virtus. Caecus hos os pneum quidne tincidunt venio. Abico iustum ludus olim tincidunt.\n\nBrevitas dignissim feugiat haero laoreet luptatum nunc secundum sed. Damnum immitto rusticus. Accumsan minim quidne torqueo. Abluo dignissim luctus nisl quadrum.\n\nEum quidne sino. Eros esse illum loquor os quidem tincidunt. Ille quia sagaciter suscipere. Esca facilisis tamen. Ad bene et genitus hos metuo premo refero sino validus. Paratus proprius secundum. Ex ideo lobortis saepius suscipere vindico. Ille obruo pala scisco.\n\nDolor luptatum neo paulatim scisco te tego vulputate. Consequat qui voco. Antehabeo cui melior nunc vicis. Accumsan dolus duis eum interdico ratis voco. Abdo amet facilisis ideo magna pagus pala rusticus vereor vulpes.\n\n"
        }
    ],
    "field_image": [
        {
            "alt": "Aliquam damnum luctus meus paulatim quidne saluto.",
            "title": "Enim imputo laoreet praesent quidne veniam zelus.",
            "width": 416,
            "height": 350,
            "target_type": "file",
            "target_uuid": "08662303-88ad-41b0-93bc-fbc0dba07cd4"
        }
    ]
}