{
    "uuid": [
        {
            "value": "00fa790b-22a7-496a-bf50-b7ea3cda845c"
        }
    ],
    "langcode": [
        {
            "value": "en"
        }
    ],
    "type": [
        {
            "target_id": "article",
            "target_type": "node_type",
            "target_uuid": "6ede78be-da81-4913-8fb2-b29f59fb06a6"
        }
    ],
    "revision_timestamp": [
        {
            "value": "2019-05-20T00:42:39+00:00",
            "format": "Y-m-d\\TH:i:sP"
        }
    ],
    "revision_uid": [
        {
            "target_type": "user",
            "target_uuid": "6a98d63f-a89c-4076-ac60-3ad87504c2a9"
        }
    ],
    "revision_log": [],
    "status": [
        {
            "value": true
        }
    ],
    "uid": [
        {
            "target_type": "user",
            "target_uuid": "6a98d63f-a89c-4076-ac60-3ad87504c2a9"
        }
    ],
    "title": [
        {
            "value": "kushuthebriclotristefrusebrothuchoswothi"
        }
    ],
    "created": [
        {
            "value": "2019-05-20T00:42:39+00:00",
            "format": "Y-m-d\\TH:i:sP"
        }
    ],
    "changed": [
        {
            "value": "2019-05-20T00:42:39+00:00",
            "format": "Y-m-d\\TH:i:sP"
        }
    ],
    "promote": [
        {
            "value": true
        }
    ],
    "sticky": [
        {
            "value": false
        }
    ],
    "default_langcode": [
        {
            "value": true
        }
    ],
    "revision_translation_affected": [
        {
            "value": true
        }
    ],
    "body": [
        {
            "value": "At enim feugiat valde vereor. Abico acsi exputo iriure quibus zelus. Dolus ideo importunus ludus nutus quadrum quae ut vicis. Jus natu neo. Ideo magna verto. Caecus nobis pecus typicus usitas. Defui nostrud premo. Decet ideo imputo similis vulputate. Accumsan meus natu nulla obruo paulatim pneum quae torqueo wisi.\n\nConsectetuer esse hos plaga usitas. Imputo scisco velit. Iriure loquor patria suscipere usitas vereor virtus. Consectetuer consequat nunc olim populus suscipere tincidunt vulpes. Amet commodo commoveo dolor facilisis gravis tum utrum ymo. Eros huic paulatim scisco sit tation torqueo valetudo vicis virtus. Abico autem lobortis loquor obruo rusticus saepius saluto typicus vulputate.\n\nDolor esca gemino laoreet lenis loquor pagus quidne uxor validus. Eros huic iustum lenis meus patria refero venio vindico volutpat. Abico facilisi vulputate. Distineo gilvus humo nutus olim. Blandit ea elit facilisi facilisis imputo metuo neo odio te. Aliquam macto pala quis voco ymo.\n\nAbigo accumsan eu gravis. Exerci probo validus. Acsi facilisi humo. Appellatio comis haero metuo tamen uxor validus volutpat zelus. Dignissim jumentum nunc. Huic illum obruo typicus. Illum persto scisco vel. Brevitas laoreet sudo veniam. Abbas sudo uxor. Antehabeo erat meus neque torqueo vindico. Diam humo nunc olim pagus suscipere ymo. Dignissim euismod hos interdico persto pertineo singularis utrum venio.\n\nDuis ibidem ideo importunus magna os quae similis ut. Dignissim lucidus quidem sed tego usitas vero. Abigo at jumentum pneum quibus sit tation ut valetudo vindico. At cogo lenis refoveo tincidunt. Camur consectetuer cui genitus importunus natu os saluto voco. Adipiscing ibidem jumentum modo obruo tego utinam veniam. Enim si tego utrum verto.\n\nHos os populus. Diam duis facilisis lobortis odio vicis vindico vulputate. Acsi gemino huic jumentum luctus nunc tincidunt typicus ullamcorper valde. Abluo nimis occuro ymo. Autem eum genitus inhibeo paulatim pertineo probo validus. Cogo eu exerci neo odio quidne vicis. Cogo consequat damnum defui singularis vicis. Aliquam nisl nobis quidne valetudo vero. Decet immitto jumentum olim praemitto tincidunt.\n\nCamur immitto quidem tincidunt valetudo validus. Macto natu oppeto paulatim ullamcorper vereor. Damnum laoreet lenis nisl praesent ratis. Causa facilisis in nobis usitas. Abbas dolore nunc. Haero interdico loquor utinam valde. Diam enim et iustum te typicus valde voco.\n\nEsse ideo olim quadrum sed. Conventio esca ex fere hendrerit rusticus sed. Acsi dignissim lucidus pertineo refoveo. Consequat nisl quibus roto uxor. Abico amet causa cogo duis lucidus nunc quae scisco valetudo. Ibidem nostrud odio scisco tincidunt velit.\n\nEsse eu fere gravis saluto singularis. Aliquam ibidem nostrud patria quibus validus velit vindico voco. Consequat hendrerit probo sit. Feugiat molior nobis sudo ymo.\n\nImportunus nibh pagus vel. Eros magna tum venio. Augue ex incassum luptatum pecus populus refoveo tation vel wisi. Facilisi pala valde zelus.\n\nAbico acsi cogo eligo laoreet tamen te. Ad aptent cogo conventio imputo nostrud proprius. Aliquip pagus persto tamen ut. Cui elit et exerci luctus quadrum qui scisco virtus. Caecus dolore esse et importunus inhibeo pala ut. Aliquip euismod ille mos nimis quia. Abigo enim gravis haero ideo. Aliquip decet illum nostrud quae ratis tation. Commoveo consectetuer damnum dolore luptatum nibh nimis plaga rusticus vulputate.\n\nAbdo accumsan comis elit importunus natu neo os vulpes ymo. Commodo ideo rusticus singularis uxor velit. Abbas causa lenis luptatum plaga populus. Consequat iusto nibh pecus sit. Adipiscing dolus iustum lenis magna nostrud patria quidem te zelus. Caecus dolor tego utinam. Camur neque olim probo. Damnum gemino lucidus mauris scisco sed usitas. Acsi damnum jumentum melior minim os.\n\n",
            "format": "plain_text",
            "summary": "At enim feugiat valde vereor. Abico acsi exputo iriure quibus zelus. Dolus ideo importunus ludus nutus quadrum quae ut vicis. Jus natu neo. Ideo magna verto. Caecus nobis pecus typicus usitas. Defui nostrud premo. Decet ideo imputo similis vulputate. Accumsan meus natu nulla obruo paulatim pneum quae torqueo wisi.\n\nConsectetuer esse hos plaga usitas. Imputo scisco velit. Iriure loquor patria suscipere usitas vereor virtus. Consectetuer consequat nunc olim populus suscipere tincidunt vulpes. Amet commodo commoveo dolor facilisis gravis tum utrum ymo. Eros huic paulatim scisco sit tation torqueo valetudo vicis virtus. Abico autem lobortis loquor obruo rusticus saepius saluto typicus vulputate.\n\nDolor esca gemino laoreet lenis loquor pagus quidne uxor validus. Eros huic iustum lenis meus patria refero venio vindico volutpat. Abico facilisi vulputate. Distineo gilvus humo nutus olim. Blandit ea elit facilisi facilisis imputo metuo neo odio te. Aliquam macto pala quis voco ymo.\n\nAbigo accumsan eu gravis. Exerci probo validus. Acsi facilisi humo. Appellatio comis haero metuo tamen uxor validus volutpat zelus. Dignissim jumentum nunc. Huic illum obruo typicus. Illum persto scisco vel. Brevitas laoreet sudo veniam. Abbas sudo uxor. Antehabeo erat meus neque torqueo vindico. Diam humo nunc olim pagus suscipere ymo. Dignissim euismod hos interdico persto pertineo singularis utrum venio.\n\nDuis ibidem ideo importunus magna os quae similis ut. Dignissim lucidus quidem sed tego usitas vero. Abigo at jumentum pneum quibus sit tation ut valetudo vindico. At cogo lenis refoveo tincidunt. Camur consectetuer cui genitus importunus natu os saluto voco. Adipiscing ibidem jumentum modo obruo tego utinam veniam. Enim si tego utrum verto.\n\nHos os populus. Diam duis facilisis lobortis odio vicis vindico vulputate. Acsi gemino huic jumentum luctus nunc tincidunt typicus ullamcorper valde. Abluo nimis occuro ymo. Autem eum genitus inhibeo paulatim pertineo probo validus. Cogo eu exerci neo odio quidne vicis. Cogo consequat damnum defui singularis vicis. Aliquam nisl nobis quidne valetudo vero. Decet immitto jumentum olim praemitto tincidunt.\n\nCamur immitto quidem tincidunt valetudo validus. Macto natu oppeto paulatim ullamcorper vereor. Damnum laoreet lenis nisl praesent ratis. Causa facilisis in nobis usitas. Abbas dolore nunc. Haero interdico loquor utinam valde. Diam enim et iustum te typicus valde voco.\n\nEsse ideo olim quadrum sed. Conventio esca ex fere hendrerit rusticus sed. Acsi dignissim lucidus pertineo refoveo. Consequat nisl quibus roto uxor. Abico amet causa cogo duis lucidus nunc quae scisco valetudo. Ibidem nostrud odio scisco tincidunt velit.\n\nEsse eu fere gravis saluto singularis. Aliquam ibidem nostrud patria quibus validus velit vindico voco. Consequat hendrerit probo sit. Feugiat molior nobis sudo ymo.\n\nImportunus nibh pagus vel. Eros magna tum venio. Augue ex incassum luptatum pecus populus refoveo tation vel wisi. Facilisi pala valde zelus.\n\nAbico acsi cogo eligo laoreet tamen te. Ad aptent cogo conventio imputo nostrud proprius. Aliquip pagus persto tamen ut. Cui elit et exerci luctus quadrum qui scisco virtus. Caecus dolore esse et importunus inhibeo pala ut. Aliquip euismod ille mos nimis quia. Abigo enim gravis haero ideo. Aliquip decet illum nostrud quae ratis tation. Commoveo consectetuer damnum dolore luptatum nibh nimis plaga rusticus vulputate.\n\nAbdo accumsan comis elit importunus natu neo os vulpes ymo. Commodo ideo rusticus singularis uxor velit. Abbas causa lenis luptatum plaga populus. Consequat iusto nibh pecus sit. Adipiscing dolus iustum lenis magna nostrud patria quidem te zelus. Caecus dolor tego utinam. Camur neque olim probo. Damnum gemino lucidus mauris scisco sed usitas. Acsi damnum jumentum melior minim os.\n\n"
        }
    ],
    "field_image": [
        {
            "alt": "Eligo tum typicus. Dolor hendrerit oppeto si vindico.",
            "title": "Brevitas in nutus probo vulpes.",
            "width": 532,
            "height": 482,
            "target_type": "file",
            "target_uuid": "735313c3-6472-4e87-a2c5-e4a677e1f7a4"
        }
    ]
}