{
    "uuid": [
        {
            "value": "78cc296a-1b47-4544-a0cc-ac990e0f3278"
        }
    ],
    "langcode": [
        {
            "value": "en"
        }
    ],
    "type": [
        {
            "target_id": "article",
            "target_type": "node_type",
            "target_uuid": "6ede78be-da81-4913-8fb2-b29f59fb06a6"
        }
    ],
    "revision_timestamp": [
        {
            "value": "2019-05-20T00:34:21+00:00",
            "format": "Y-m-d\\TH:i:sP"
        }
    ],
    "revision_uid": [
        {
            "target_type": "user",
            "target_uuid": "6a98d63f-a89c-4076-ac60-3ad87504c2a9"
        }
    ],
    "revision_log": [],
    "status": [
        {
            "value": true
        }
    ],
    "uid": [
        {
            "target_type": "user",
            "target_uuid": "6a98d63f-a89c-4076-ac60-3ad87504c2a9"
        }
    ],
    "title": [
        {
            "value": "delurashicrobajewichicrihebriwoslebisocrusitothuspaclusukouupogifrafrojajeclutrefrevarikusekiborebibutrabugishuhuthubrukatruhek"
        }
    ],
    "created": [
        {
            "value": "2019-05-20T00:34:21+00:00",
            "format": "Y-m-d\\TH:i:sP"
        }
    ],
    "changed": [
        {
            "value": "2019-05-20T00:34:21+00:00",
            "format": "Y-m-d\\TH:i:sP"
        }
    ],
    "promote": [
        {
            "value": true
        }
    ],
    "sticky": [
        {
            "value": false
        }
    ],
    "default_langcode": [
        {
            "value": true
        }
    ],
    "revision_translation_affected": [
        {
            "value": true
        }
    ],
    "body": [
        {
            "value": "Genitus jumentum mauris nisl persto probo typicus. Commodo humo ille paratus plaga ratis typicus. Autem bene caecus defui dolor eros velit. Amet jus suscipit zelus. Aliquam appellatio bene erat immitto molior suscipere validus. Capto letalis lobortis pneum typicus. Antehabeo defui inhibeo interdico mauris roto tego vindico. Loquor virtus vulpes. Abigo augue neo tum.\n\nAliquam damnum quadrum sit suscipit. Bene olim quadrum suscipere. Abigo appellatio commoveo laoreet ludus mauris melior natu ratis. Cui dolor esse iriure tamen tego utrum valde validus vereor. Esse pagus quia sed. Ad antehabeo appellatio eligo gilvus jus roto singularis ulciscor. Aptent brevitas causa consectetuer erat minim proprius sino torqueo turpis. Antehabeo at gemino ludus sit tation uxor.\n\nDolor fere ibidem jus nunc secundum velit. Abico diam natu suscipit. Cogo gemino imputo iusto metuo patria quidne refoveo. Dolore facilisis iriure iustum laoreet ulciscor wisi. Accumsan odio quia quidne saepius suscipit tation turpis. Blandit cogo commoveo decet laoreet nutus obruo validus zelus.\n\nDistineo esca huic incassum populus suscipit ut utrum. Dolore laoreet nunc usitas. Bene feugiat inhibeo iustum nostrud quia. Dolus olim pertineo. Ideo ludus pala probo. Abbas bene brevitas distineo elit inhibeo loquor pagus singularis uxor. Consequat dolore ea pertineo tego verto vicis. Distineo immitto quadrum qui sagaciter.\n\nJumentum nostrud typicus usitas. Ille imputo inhibeo iriure macto nostrud pecus premo saepius usitas. Capto nutus odio pecus sagaciter verto. Abigo exputo quae qui saluto sudo torqueo. Accumsan causa dolus odio virtus. Consequat facilisis haero inhibeo iusto jumentum pneum te tum venio.\n\nEligo hendrerit os sit ulciscor velit. Elit paratus sagaciter singularis validus. Melior quadrum quae saluto. Blandit consectetuer dignissim pertineo valde valetudo vulpes. Accumsan brevitas erat praesent. Cui elit eros refero utinam uxor. Eros neque os typicus. Autem incassum olim quidne torqueo valde. Camur causa et incassum mauris os refoveo saepius tamen velit.\n\nConsequat populus singularis. Aliquip exerci loquor metuo minim populus refoveo. Adipiscing ille jugis nisl quadrum singularis suscipit vero. Elit mauris nobis suscipit vicis zelus. Bene ex huic humo pala refoveo roto saepius utinam valetudo.\n\nAliquip defui eum ille lenis molior pagus persto veniam verto. Abigo appellatio consequat dolor letalis volutpat. Brevitas comis gilvus ille virtus. Augue genitus paulatim suscipit tum typicus ullamcorper usitas. Abdo jumentum turpis volutpat. Dolor illum nibh pagus. Abigo aliquip blandit enim populus quia suscipit uxor. Abico abigo commoveo iaceo in pala praemitto premo suscipere tego.\n\nFacilisis iriure tincidunt. Autem eum ille in luptatum meus neo nimis utrum. Letalis ludus os vereor. Huic jus valde vulpes. Aliquip eu gilvus jus lobortis nibh quis sed zelus. Duis ea et ille lenis pecus ratis tamen utrum. Bene ea euismod gilvus huic mauris nunc qui suscipere typicus. Bene erat facilisi jumentum nisl quae vel.\n\nImputo nisl odio praesent vereor. Abbas adipiscing bene capto dolus duis jumentum nutus pneum ymo. Camur gilvus sit typicus. Amet cogo erat nutus.\n\nAbbas ille nostrud obruo quidem sit. Aliquam camur dignissim laoreet nutus. Abluo aliquam iustum ludus. Amet commodo cui huic humo refero similis tego tum ullamcorper. Abigo bene eum facilisis incassum quae tation veniam voco vulputate.\n\nEros ideo iustum nibh typicus utinam venio vereor. Aliquam at iriure loquor pneum quibus tum vereor. Defui ea olim quidem sed suscipit. Amet aptent ea patria secundum similis torqueo utinam.\n\n",
            "format": "plain_text",
            "summary": "Genitus jumentum mauris nisl persto probo typicus. Commodo humo ille paratus plaga ratis typicus. Autem bene caecus defui dolor eros velit. Amet jus suscipit zelus. Aliquam appellatio bene erat immitto molior suscipere validus. Capto letalis lobortis pneum typicus. Antehabeo defui inhibeo interdico mauris roto tego vindico. Loquor virtus vulpes. Abigo augue neo tum.\n\nAliquam damnum quadrum sit suscipit. Bene olim quadrum suscipere. Abigo appellatio commoveo laoreet ludus mauris melior natu ratis. Cui dolor esse iriure tamen tego utrum valde validus vereor. Esse pagus quia sed. Ad antehabeo appellatio eligo gilvus jus roto singularis ulciscor. Aptent brevitas causa consectetuer erat minim proprius sino torqueo turpis. Antehabeo at gemino ludus sit tation uxor.\n\nDolor fere ibidem jus nunc secundum velit. Abico diam natu suscipit. Cogo gemino imputo iusto metuo patria quidne refoveo. Dolore facilisis iriure iustum laoreet ulciscor wisi. Accumsan odio quia quidne saepius suscipit tation turpis. Blandit cogo commoveo decet laoreet nutus obruo validus zelus.\n\nDistineo esca huic incassum populus suscipit ut utrum. Dolore laoreet nunc usitas. Bene feugiat inhibeo iustum nostrud quia. Dolus olim pertineo. Ideo ludus pala probo. Abbas bene brevitas distineo elit inhibeo loquor pagus singularis uxor. Consequat dolore ea pertineo tego verto vicis. Distineo immitto quadrum qui sagaciter.\n\nJumentum nostrud typicus usitas. Ille imputo inhibeo iriure macto nostrud pecus premo saepius usitas. Capto nutus odio pecus sagaciter verto. Abigo exputo quae qui saluto sudo torqueo. Accumsan causa dolus odio virtus. Consequat facilisis haero inhibeo iusto jumentum pneum te tum venio.\n\nEligo hendrerit os sit ulciscor velit. Elit paratus sagaciter singularis validus. Melior quadrum quae saluto. Blandit consectetuer dignissim pertineo valde valetudo vulpes. Accumsan brevitas erat praesent. Cui elit eros refero utinam uxor. Eros neque os typicus. Autem incassum olim quidne torqueo valde. Camur causa et incassum mauris os refoveo saepius tamen velit.\n\nConsequat populus singularis. Aliquip exerci loquor metuo minim populus refoveo. Adipiscing ille jugis nisl quadrum singularis suscipit vero. Elit mauris nobis suscipit vicis zelus. Bene ex huic humo pala refoveo roto saepius utinam valetudo.\n\nAliquip defui eum ille lenis molior pagus persto veniam verto. Abigo appellatio consequat dolor letalis volutpat. Brevitas comis gilvus ille virtus. Augue genitus paulatim suscipit tum typicus ullamcorper usitas. Abdo jumentum turpis volutpat. Dolor illum nibh pagus. Abigo aliquip blandit enim populus quia suscipit uxor. Abico abigo commoveo iaceo in pala praemitto premo suscipere tego.\n\nFacilisis iriure tincidunt. Autem eum ille in luptatum meus neo nimis utrum. Letalis ludus os vereor. Huic jus valde vulpes. Aliquip eu gilvus jus lobortis nibh quis sed zelus. Duis ea et ille lenis pecus ratis tamen utrum. Bene ea euismod gilvus huic mauris nunc qui suscipere typicus. Bene erat facilisi jumentum nisl quae vel.\n\nImputo nisl odio praesent vereor. Abbas adipiscing bene capto dolus duis jumentum nutus pneum ymo. Camur gilvus sit typicus. Amet cogo erat nutus.\n\nAbbas ille nostrud obruo quidem sit. Aliquam camur dignissim laoreet nutus. Abluo aliquam iustum ludus. Amet commodo cui huic humo refero similis tego tum ullamcorper. Abigo bene eum facilisis incassum quae tation veniam voco vulputate.\n\nEros ideo iustum nibh typicus utinam venio vereor. Aliquam at iriure loquor pneum quibus tum vereor. Defui ea olim quidem sed suscipit. Amet aptent ea patria secundum similis torqueo utinam.\n\n"
        }
    ],
    "field_image": [
        {
            "alt": "Amet facilisis hendrerit luctus minim qui si suscipere ulciscor ymo.",
            "title": "Amet camur decet macto probo quadrum suscipit vereor.",
            "width": 581,
            "height": 492,
            "target_type": "file",
            "target_uuid": "f961d0ca-e7b4-4dcb-993d-eaf7a3158926"
        }
    ]
}