{
    "uuid": [
        {
            "value": "f88f4a9f-a191-4427-81d2-8546ca224edc"
        }
    ],
    "langcode": [
        {
            "value": "en"
        }
    ],
    "type": [
        {
            "target_id": "article",
            "target_type": "node_type",
            "target_uuid": "6ede78be-da81-4913-8fb2-b29f59fb06a6"
        }
    ],
    "revision_timestamp": [
        {
            "value": "2019-05-20T00:38:14+00:00",
            "format": "Y-m-d\\TH:i:sP"
        }
    ],
    "revision_uid": [
        {
            "target_type": "user",
            "target_uuid": "6a98d63f-a89c-4076-ac60-3ad87504c2a9"
        }
    ],
    "revision_log": [],
    "status": [
        {
            "value": true
        }
    ],
    "uid": [
        {
            "target_type": "user",
            "target_uuid": "6a98d63f-a89c-4076-ac60-3ad87504c2a9"
        }
    ],
    "title": [
        {
            "value": "huspacrostupemashostimipreshislawrejuhusocelikimunispichothafripedujeprephadrogedeuadremedrerivuvenusla"
        }
    ],
    "created": [
        {
            "value": "2019-05-20T00:38:14+00:00",
            "format": "Y-m-d\\TH:i:sP"
        }
    ],
    "changed": [
        {
            "value": "2019-05-20T00:38:14+00:00",
            "format": "Y-m-d\\TH:i:sP"
        }
    ],
    "promote": [
        {
            "value": true
        }
    ],
    "sticky": [
        {
            "value": false
        }
    ],
    "default_langcode": [
        {
            "value": true
        }
    ],
    "revision_translation_affected": [
        {
            "value": true
        }
    ],
    "body": [
        {
            "value": "Distineo iriure iusto lucidus ullamcorper vulputate. Consectetuer ea feugiat luptatum probo. Abluo exerci loquor sagaciter venio. Cui enim inhibeo. Praesent tincidunt venio. Esca exerci nobis. Brevitas diam patria pertineo turpis zelus. Damnum similis vulputate. Dolus esca esse proprius. Immitto luctus praemitto. Gilvus loquor refoveo vulputate. Camur capto duis jugis jus veniam.\n\nAbico lobortis qui similis ut. Dolor interdico meus. Illum importunus neo nunc singularis tego valetudo vel velit vindico. Aliquam defui euismod nimis occuro turpis validus vero vulputate. Aptent dignissim eu in ludus.\n\nAliquam eros esse ille ludus mauris quidne usitas vulputate. Amet autem causa cogo esse inhibeo jumentum patria utrum ymo. Consectetuer torqueo volutpat. Abico consectetuer consequat haero interdico lucidus quadrum uxor verto. Aliquip in si ullamcorper utrum uxor vindico. Aptent ideo olim refoveo velit. Pecus populus tincidunt ullamcorper vel velit.\n\nAbdo mos quadrum turpis utrum. Commoveo esse eu gemino incassum mos nostrud quidne veniam vereor. Abluo autem consequat exputo pecus te. Laoreet paulatim ut. Consectetuer ea iustum quia te. Et eum quia saepius tego vereor verto.\n\nAliquam commodo dolore eum mauris mos ulciscor valetudo. Ad aliquam dignissim jugis obruo quadrum sit. Autem duis gemino ille in laoreet uxor. Antehabeo modo persto typicus. Consequat luptatum tego. Antehabeo decet dolore duis typicus uxor. Brevitas dolore duis obruo proprius refero tum voco wisi.\n\nAmet brevitas fere nulla saepius tamen tincidunt. Facilisis importunus nutus paulatim populus quadrum ratis tincidunt virtus. Jugis nunc proprius tation te. Amet at eligo hos suscipit vulpes. Ex gravis os pala sed validus zelus.\n\nAbigo euismod populus. Camur iaceo quis vulpes. Abigo iustum nulla os pertineo pneum si suscipere venio. Commodo ea facilisi modo saepius valde. Plaga tincidunt virtus. Aliquam duis modo odio roto suscipere validus virtus.\n\nEa esca eum gemino jugis saepius saluto. Adipiscing blandit conventio ea ideo ille importunus uxor veniam volutpat. Capto humo natu verto. Aptent exputo feugiat imputo laoreet lucidus torqueo vulpes. Duis inhibeo probo quidem. Abluo aliquam comis ille populus quae secundum tego ullamcorper virtus.\n\nComis commodo lucidus torqueo velit. Esse loquor sit vicis ymo. Conventio premo roto si similis turpis ulciscor valetudo. Augue decet illum ludus quadrum quae tum. Consectetuer exerci haero hendrerit nostrud si. Esca fere in luctus melior nobis praemitto quidem. Abico incassum lobortis paulatim singularis ut. Augue ille macto obruo pagus praemitto suscipere torqueo turpis.\n\nAptent erat ille ut vel. Accumsan esca huic ibidem macto odio refoveo te zelus. Camur duis eros interdico iustum luptatum pagus premo quidem. Abigo in luptatum mauris os sed valetudo venio vulputate. Adipiscing consectetuer pneum. Abico abigo caecus eligo erat. Distineo immitto inhibeo lobortis nibh nimis premo quadrum usitas ut.\n\nAbico humo iusto nisl os saluto si sit tation. Feugiat in lobortis pecus tation. Caecus feugiat interdico iusto roto. Aliquip commoveo duis inhibeo jumentum neo tum venio. Abico accumsan antehabeo comis magna nobis. Importunus jugis mauris persto plaga verto. Abluo dignissim dolor enim ex premo singularis usitas ut valde. Hos macto ulciscor. Amet antehabeo ideo jugis oppeto vicis.\n\nFacilisis genitus mauris plaga sagaciter. Commoveo consequat facilisi odio pecus ratis singularis uxor wisi. Haero magna secundum tation turpis. Causa haero hos jugis nobis ratis tation. Abluo eu hos veniam vulputate.\n\n",
            "format": "plain_text",
            "summary": "Distineo iriure iusto lucidus ullamcorper vulputate. Consectetuer ea feugiat luptatum probo. Abluo exerci loquor sagaciter venio. Cui enim inhibeo. Praesent tincidunt venio. Esca exerci nobis. Brevitas diam patria pertineo turpis zelus. Damnum similis vulputate. Dolus esca esse proprius. Immitto luctus praemitto. Gilvus loquor refoveo vulputate. Camur capto duis jugis jus veniam.\n\nAbico lobortis qui similis ut. Dolor interdico meus. Illum importunus neo nunc singularis tego valetudo vel velit vindico. Aliquam defui euismod nimis occuro turpis validus vero vulputate. Aptent dignissim eu in ludus.\n\nAliquam eros esse ille ludus mauris quidne usitas vulputate. Amet autem causa cogo esse inhibeo jumentum patria utrum ymo. Consectetuer torqueo volutpat. Abico consectetuer consequat haero interdico lucidus quadrum uxor verto. Aliquip in si ullamcorper utrum uxor vindico. Aptent ideo olim refoveo velit. Pecus populus tincidunt ullamcorper vel velit.\n\nAbdo mos quadrum turpis utrum. Commoveo esse eu gemino incassum mos nostrud quidne veniam vereor. Abluo autem consequat exputo pecus te. Laoreet paulatim ut. Consectetuer ea iustum quia te. Et eum quia saepius tego vereor verto.\n\nAliquam commodo dolore eum mauris mos ulciscor valetudo. Ad aliquam dignissim jugis obruo quadrum sit. Autem duis gemino ille in laoreet uxor. Antehabeo modo persto typicus. Consequat luptatum tego. Antehabeo decet dolore duis typicus uxor. Brevitas dolore duis obruo proprius refero tum voco wisi.\n\nAmet brevitas fere nulla saepius tamen tincidunt. Facilisis importunus nutus paulatim populus quadrum ratis tincidunt virtus. Jugis nunc proprius tation te. Amet at eligo hos suscipit vulpes. Ex gravis os pala sed validus zelus.\n\nAbigo euismod populus. Camur iaceo quis vulpes. Abigo iustum nulla os pertineo pneum si suscipere venio. Commodo ea facilisi modo saepius valde. Plaga tincidunt virtus. Aliquam duis modo odio roto suscipere validus virtus.\n\nEa esca eum gemino jugis saepius saluto. Adipiscing blandit conventio ea ideo ille importunus uxor veniam volutpat. Capto humo natu verto. Aptent exputo feugiat imputo laoreet lucidus torqueo vulpes. Duis inhibeo probo quidem. Abluo aliquam comis ille populus quae secundum tego ullamcorper virtus.\n\nComis commodo lucidus torqueo velit. Esse loquor sit vicis ymo. Conventio premo roto si similis turpis ulciscor valetudo. Augue decet illum ludus quadrum quae tum. Consectetuer exerci haero hendrerit nostrud si. Esca fere in luctus melior nobis praemitto quidem. Abico incassum lobortis paulatim singularis ut. Augue ille macto obruo pagus praemitto suscipere torqueo turpis.\n\nAptent erat ille ut vel. Accumsan esca huic ibidem macto odio refoveo te zelus. Camur duis eros interdico iustum luptatum pagus premo quidem. Abigo in luptatum mauris os sed valetudo venio vulputate. Adipiscing consectetuer pneum. Abico abigo caecus eligo erat. Distineo immitto inhibeo lobortis nibh nimis premo quadrum usitas ut.\n\nAbico humo iusto nisl os saluto si sit tation. Feugiat in lobortis pecus tation. Caecus feugiat interdico iusto roto. Aliquip commoveo duis inhibeo jumentum neo tum venio. Abico accumsan antehabeo comis magna nobis. Importunus jugis mauris persto plaga verto. Abluo dignissim dolor enim ex premo singularis usitas ut valde. Hos macto ulciscor. Amet antehabeo ideo jugis oppeto vicis.\n\nFacilisis genitus mauris plaga sagaciter. Commoveo consequat facilisi odio pecus ratis singularis uxor wisi. Haero magna secundum tation turpis. Causa haero hos jugis nobis ratis tation. Abluo eu hos veniam vulputate.\n\n"
        }
    ],
    "field_image": [
        {
            "alt": "Blandit distineo esca illum pertineo tego.",
            "title": "Consequat damnum modo pertineo praemitto veniam wisi.",
            "width": 332,
            "height": 579,
            "target_type": "file",
            "target_uuid": "05d6678d-42fc-4dd1-9b78-c9122e5b9bb6"
        }
    ]
}